sphinxcontrib_ssmlbuilder-0.2.0-py3.6-nspkg.pth
sphinxcontrib/builder.py
sphinxcontrib/ssmlbuilder.py
sphinxcontrib/throttling.py
sphinxcontrib/writer.py
sphinxcontrib_ssmlbuilder-0.2.0.dist-info/DESCRIPTION.rst
sphinxcontrib_ssmlbuilder-0.2.0.dist-info/METADATA
sphinxcontrib_ssmlbuilder-0.2.0.dist-info/RECORD
sphinxcontrib_ssmlbuilder-0.2.0.dist-info/WHEEL
sphinxcontrib_ssmlbuilder-0.2.0.dist-info/metadata.json
sphinxcontrib_ssmlbuilder-0.2.0.dist-info/namespace_packages.txt
sphinxcontrib_ssmlbuilder-0.2.0.dist-info/top_level.txt
